quotescli/__init__.py
quotescli/__main__.py
quotescli/main.py
quotescli-0.2.0.dist-info/METADATA
quotescli-0.2.0.dist-info/WHEEL
quotescli-0.2.0.dist-info/top_level.txt
quotescli-0.2.0.dist-info/RECORD
