Metadata-Version: 2.1
Name: quotescli
Version: 0.2.0
Summary: A Python CLI tool for displaying Quotes
Home-page: UNKNOWN
Author: ramsy (Mohamed Said EL-yemlahi)
Author-email: <0ramsy0@gmail.com>
License: UNKNOWN
Keywords: Quotes,Python,scraping,notification,cli
Platform: UNKNOWN
Classifier: Development Status :: 1 - Planning
Classifier: Intended Audience :: Developers
Classifier: Programming Language :: Python :: 3
Classifier: Operating System :: Unix
Classifier: Operating System :: MacOS :: MacOS X
Classifier: Operating System :: Microsoft :: Windows
Requires-Dist: bs4
Requires-Dist: colorama
Requires-Dist: prettytable
Requires-Dist: pyler
